carbon/__init__.py
carbon/client/__init__.py
carbon/client/async_udp.py
carbon/client/compat.py
carbon/client/extras.py
carbon/client/udp.py
carbon/client/decorators/__init__.py
carbon/client/decorators/timeit.py
carbon/client/metrics/__init__.py
carbon/client/metrics/base.py
carbon/client/metrics/collector.py
carbon/client/metrics/heartbeat.py
carbon/client/metrics/simple.py
carbon/client/metrics/timer.py
carbon_client-0.3.1.dist-info/DESCRIPTION.rst
carbon_client-0.3.1.dist-info/METADATA
carbon_client-0.3.1.dist-info/RECORD
carbon_client-0.3.1.dist-info/WHEEL
carbon_client-0.3.1.dist-info/metadata.json
carbon_client-0.3.1.dist-info/top_level.txt
