Metadata-Version: 2.0
Name: carbon-client
Version: 0.3.1
Summary: graphite/carbon udp client for sending metrics
Home-page: http://github.com/mosquito/carbon-client
Author: Dmitry Orlov <me@mosquito.su>
Author-email: me@mosquito.su
License: MIT
Platform: all
Classifier: Environment :: Console
Classifier: Programming Language :: Python
Classifier: Programming Language :: Python :: 2.7
Classifier: Programming Language :: Python :: 3.4
Classifier: Programming Language :: Python :: 3.5
Classifier: Topic :: System :: Monitoring
Classifier: Topic :: System :: Networking :: Monitoring
Classifier: License :: OSI Approved :: MIT License
Classifier: Natural Language :: English
Classifier: Natural Language :: Russian
Classifier: Topic :: Software Development :: Libraries
Classifier: Development Status :: 4 - Beta
